vcp/__init__.py
vcp/__main__.py
vcp/cli.py
vcp/auth/__init__.py
vcp/auth/config.py
vcp/auth/github.py
vcp/auth/oauth.py
vcp/auth/token.py
vcp/commands/__init__.py
vcp/commands/cache.py
vcp/commands/config.py
vcp/commands/login.py
vcp/commands/logout.py
vcp/commands/version.py
vcp/commands/benchmarks/__init__.py
vcp/commands/benchmarks/api.py
vcp/commands/benchmarks/get.py
vcp/commands/benchmarks/list.py
vcp/commands/benchmarks/resolve_references.py
vcp/commands/benchmarks/run.py
vcp/commands/benchmarks/run_pipeline.py
vcp/commands/benchmarks/run_task.py
vcp/commands/benchmarks/specs.py
vcp/commands/benchmarks/system_check.py
vcp/commands/benchmarks/system_validator.py
vcp/commands/benchmarks/tasks_cli_handler.py
vcp/commands/benchmarks/utils.py
vcp/commands/benchmarks/stub_data/.gitignore
vcp/commands/benchmarks/stub_data/model_registry.yaml
vcp/commands/benchmarks/stub_data/results.json
vcp/commands/benchmarks/stub_data/transform_results.py
vcp/commands/data/__init__.py
vcp/commands/data/describe.py
vcp/commands/data/download.py
vcp/commands/data/preview.py
vcp/commands/data/search.py
vcp/commands/data/summary.py
vcp/commands/model/DEBUG_SUPPORT.md
vcp/commands/model/GITHUB_AUTH.md
vcp/commands/model/TESTING.md
vcp/commands/model/__init__.py
vcp/commands/model/api.py
vcp/commands/model/assist.py
vcp/commands/model/download.py
vcp/commands/model/git_operations.py
vcp/commands/model/init.py
vcp/commands/model/list.py
vcp/commands/model/models.py
vcp/commands/model/stage.py
vcp/commands/model/status.py
vcp/commands/model/submit.py
vcp/commands/model/utils.py
vcp/commands/model/validate_model_metadata.py
vcp/commands/model/workflow_assistant.py
vcp/commands/model/workspace.py
vcp/commands/model/helpers/__init__.py
vcp/commands/model/helpers/display_helpers.py
vcp/commands/model/helpers/download_helpers.py
vcp/config/__init__.py
vcp/config/config.py
vcp/config/settings.py
vcp/datasets/api.py
vcp/datasets/download.py
vcp/datasets/download_db.py
vcp/datasets/utils.py
vcp_cli-0.51.0.dist-info/METADATA
vcp_cli-0.51.0.dist-info/WHEEL
vcp_cli-0.51.0.dist-info/entry_points.txt
vcp_cli-0.51.0.dist-info/RECORD
