Metadata-Version: 2.4
Name: vcp-cli
Version: 0.51.0
Summary: VCP CLI - A command-line interface (CLI) to the Chan Zuckerberg Initiative's Virtual Cell Platform (VCP)
Author-email: Chan Zuckerberg Initiative <info@chanzuckerberg.com>
License: MIT
Requires-Python: <3.14,>=3.10
Requires-Dist: authlib>=1.0.0
Requires-Dist: boto3>=1.34.0
Requires-Dist: click>=8.0.0
Requires-Dist: cryptography>=41.0.0
Requires-Dist: packaging>=20.0
Requires-Dist: pydantic>=2.0.0
Requires-Dist: pyjwt>=2.8.0
Requires-Dist: python-dotenv>=1.0.0
Requires-Dist: pyyaml>=6.0.0
Requires-Dist: requests>=2.0.0
Requires-Dist: rich>=10.0.0
Requires-Dist: tabulate>=0.9.0
Requires-Dist: tqdm==4.67.1
Requires-Dist: werkzeug>=2.0.0
Provides-Extra: all
Requires-Dist: anndata>=0.9.0; extra == 'all'
Requires-Dist: copier>=9.9.0; extra == 'all'
Requires-Dist: cz-benchmarks~=0.15.0; extra == 'all'
Requires-Dist: gitpython>=3.1.0; extra == 'all'
Requires-Dist: mlflow>=2.0.0; extra == 'all'
Requires-Dist: mypy-boto3-s3>=1.39.2; extra == 'all'
Requires-Dist: numpy>=1.25; extra == 'all'
Provides-Extra: benchmarks
Requires-Dist: anndata>=0.9.0; extra == 'benchmarks'
Requires-Dist: cz-benchmarks~=0.15.0; extra == 'benchmarks'
Provides-Extra: data
Requires-Dist: mypy-boto3-s3>=1.39.2; extra == 'data'
Provides-Extra: model
Requires-Dist: copier>=9.9.0; extra == 'model'
Requires-Dist: gitpython>=3.1.0; extra == 'model'
Requires-Dist: mlflow>=2.0.0; extra == 'model'
Requires-Dist: numpy>=1.25; extra == 'model'
